{
  "db_name": "PostgreSQL",
  "query": "SELECT key, encrypted_value FROM secrets WHERE tenant_id = $1 AND project_id IS NULL",
  "describe": {
    "columns": [
      {
        "ordinal": 0,
        "name": "key",
        "type_info": "Text"
      },
      {
        "ordinal": 1,
        "name": "encrypted_value",
        "type_info": "Text"
      }
    ],
    "parameters": {
      "Left": [
        "Uuid"
      ]
    },
    "nullable": [
      false,
      false
    ]
  },
  "hash": "8e1a145c8d2a2bcba33148bd75d21c568375ca7c8d38f9d394def6558c729ba2"
}
